{"youtubeChannelId":"92","channelId":"122","channelTitle":"Ahmed Hamdy","playlists":[{"id":"p1221","title":"كورس أساسيات المونتاج ببرنامج أدوبي بريمير برو للكمبيوتر – للمبتدئين | Adobe Premiere Pro Video Editing Basics Course for PC - For Beginners","thumbnail":"https://i.ytimg.com/vi/VUEZfHPtom0/hqdefault.jpg","videoCount":16,"categories":["video-editing","adobe-editing"],"path":"data/playlists/chunk_001/p1221.json"},{"id":"p1222","title":"كورس مفاهيم الجرافيك ديزاين الأساسية | أحمد حمدي - Basic Graphic Design Concepts Course | Ahmed Hamdy","thumbnail":"https://i.ytimg.com/vi/fCMesgC_AQ8/hqdefault.jpg","videoCount":8,"categories":["design"],"path":"data/playlists/chunk_001/p1222.json"},{"id":"p1223","title":"كورسات كاملة في مجال المونتاج والجرافيك ديزاين - أحمد حمدي","thumbnail":"https://i.ytimg.com/vi/tCH081BrmZI/hqdefault.jpg","videoCount":6,"categories":["video-editing"],"path":"data/playlists/chunk_001/p1223.json"},{"id":"p1224","title":"مشاريع مونتاج كاملة بإستخدام كاب كات | أحمد حمدي - Complete Video Editing Projects Using CapCut | Ahmed Hamdi","thumbnail":"https://i.ytimg.com/vi/vfUdfLUCXHI/hqdefault.jpg","videoCount":3,"categories":["video-editing","capcut-editing"],"path":"data/playlists/chunk_001/p1224.json"},{"id":"p1225","title":"تعلم مهارات المونتاج باستخدام كاب كات | Learn Video Editing Skills with CapCut","thumbnail":"https://i.ytimg.com/vi/wZKyoBGdQao/hqdefault.jpg","videoCount":49,"categories":["video-editing","capcut-editing"],"path":"data/playlists/chunk_001/p1225.json"},{"id":"p1226","title":"كورس أساسيات المونتاج ببرنامج كاب كات للهاتف - للمبتدئين (Basic Video Editing Course with CapCut for Mobile - For Beginners)","thumbnail":"https://i.ytimg.com/vi/WUdqKqtVvkg/hqdefault.jpg","videoCount":18,"categories":["video-editing","capcut-editing"],"path":"data/playlists/chunk_001/p1226.json"},{"id":"p1227","title":"كورس أساسيات المونتاج ببرنامج كاب كات للكمبيوتر - للمبتدئين | CapCut Video Editing Basics Course for PC","thumbnail":"https://i.ytimg.com/vi/qrLKr-811es/hqdefault.jpg","videoCount":24,"categories":["video-editing","capcut-editing"],"path":"data/playlists/chunk_001/p1227.json"},{"id":"p1228","title":"كورس مفاهيم الفيديو والمونتاج الأساسية - Video and Basic Editing Concepts Course","thumbnail":"https://i.ytimg.com/vi/IE0z0IFJGa8/hqdefault.jpg","videoCount":10,"categories":["video-editing"],"path":"data/playlists/chunk_001/p1228.json"}]}