{"youtubeChannelId":"UCSNkfKl4cU-55Nm-ovsvOHQ","channelId":"3","channelTitle":"Elzero Web School","playlists":[{"id":"p31","title":"Implement Functions With C++","thumbnail":"https://i.ytimg.com/vi/cTvqNc82NJ0/hqdefault.jpg","videoCount":28,"channelTitle":"Elzero Web School","categories":["programming","cpp-programming"],"path":"data/playlists/chunk_001/p31.json"},{"id":"p32","title":"Problems Solving With C++ Level Two","thumbnail":"https://i.ytimg.com/vi/KuYWBFsmNmI/hqdefault.jpg","videoCount":32,"channelTitle":"Elzero Web School","categories":["programming","cpp-programming"],"path":"data/playlists/chunk_001/p32.json"},{"id":"p33","title":"Hangman Game","thumbnail":"https://i.ytimg.com/vi/kWhXAtj2M6s/hqdefault.jpg","videoCount":9,"channelTitle":"Elzero Web School","categories":["programming","web","backend"],"path":"data/playlists/chunk_001/p33.json"},{"id":"p34","title":"Memory Blocks Game","thumbnail":"https://i.ytimg.com/vi/41i0LS9Xy-o/hqdefault.jpg","videoCount":10,"channelTitle":"Elzero Web School","categories":["programming","web","backend"],"path":"data/playlists/chunk_001/p34.json"},{"id":"p35","title":"Guess The Word Game","thumbnail":"https://i.ytimg.com/vi/3AI_nIuGp4s/hqdefault.jpg","videoCount":8,"channelTitle":"Elzero Web School","categories":["programming","web","backend"],"path":"data/playlists/chunk_001/p35.json"},{"id":"p36","title":"CSS Useful Features","thumbnail":"https://i.ytimg.com/vi/-2UNIZ0dTk8/hqdefault.jpg","videoCount":14,"channelTitle":"Elzero Web School","categories":["programming","web","frontend"],"path":"data/playlists/chunk_001/p36.json"},{"id":"p37","title":"Problems Solving With C++ Level One","thumbnail":"https://i.ytimg.com/vi/YwiXDtIJ9Vo/hqdefault.jpg","videoCount":35,"channelTitle":"Elzero Web School","categories":["programming","cpp-programming"],"path":"data/playlists/chunk_001/p37.json"},{"id":"p38","title":"Fundamentals Of Programming With C++","thumbnail":"https://i.ytimg.com/vi/XDuWyYxksXU/hqdefault.jpg","videoCount":78,"channelTitle":"Elzero Web School","categories":["programming","cpp-programming"],"path":"data/playlists/chunk_001/p38.json"},{"id":"p39","title":"Codewars Problems Solving","thumbnail":"https://i.ytimg.com/vi/VlLY0RAx-LQ/hqdefault.jpg","videoCount":4,"channelTitle":"Elzero Web School","categories":["programming"],"path":"data/playlists/chunk_001/p39.json"},{"id":"p310","title":"HTML And CSS Template 4","thumbnail":"https://i.ytimg.com/vi/4OGWPn-Q__I/hqdefault.jpg","videoCount":34,"channelTitle":"Elzero Web School","categories":["programming","web","frontend"],"path":"data/playlists/chunk_001/p310.json"},{"id":"p311","title":"Back-End Developer Roadmap","thumbnail":"https://i.ytimg.com/vi/qfPUMV9J5yw/hqdefault.jpg","videoCount":1,"channelTitle":"Elzero Web School","categories":["programming","web","backend"],"path":"data/playlists/chunk_001/p311.json"},{"id":"p312","title":"Front-End Developer Roadmap","thumbnail":"https://i.ytimg.com/vi/qfPUMV9J5yw/hqdefault.jpg","videoCount":8,"channelTitle":"Elzero Web School","categories":["programming","web","frontend"],"path":"data/playlists/chunk_001/p312.json"},{"id":"p313","title":"Learn Typescript 2022","thumbnail":"https://i.ytimg.com/vi/yUndnE-2osg/hqdefault.jpg","videoCount":38,"channelTitle":"Elzero Web School","categories":["programming"],"path":"data/playlists/chunk_001/p313.json"},{"id":"p314","title":"Implement Built-In Functions Yourself","thumbnail":"https://i.ytimg.com/vi/G0iURVjGMVM/hqdefault.jpg","videoCount":9,"channelTitle":"Elzero Web School","categories":["programming"],"path":"data/playlists/chunk_001/p314.json"},{"id":"p315","title":"PHP Bootcamp 2022","thumbnail":"https://i.ytimg.com/vi/xcg9qq6SZ0w/hqdefault.jpg","videoCount":105,"channelTitle":"Elzero Web School","categories":["programming","backend"],"path":"data/playlists/chunk_001/p315.json"},{"id":"p316","title":"Bootstrap 5 Design 01 Bondi","thumbnail":"https://i.ytimg.com/vi/9mdGUKFu5OQ/hqdefault.jpg","videoCount":12,"channelTitle":"Elzero Web School","categories":["programming","web","frontend"],"path":"data/playlists/chunk_001/p316.json"},{"id":"p317","title":"Learn SASS In Arabic 2021","thumbnail":"https://i.ytimg.com/vi/Di_RlcpkpN4/hqdefault.jpg","videoCount":19,"channelTitle":"Elzero Web School","categories":["programming"],"path":"data/playlists/chunk_001/p317.json"},{"id":"p318","title":"HTML And CSS Template 3","thumbnail":"https://i.ytimg.com/vi/lXVP3rDH9EU/hqdefault.jpg","videoCount":33,"channelTitle":"Elzero Web School","categories":["programming","web","frontend"],"path":"data/playlists/chunk_001/p318.json"},{"id":"p319","title":"Problems Solving","thumbnail":"https://i.ytimg.com/vi/CnFaB06cHH0/hqdefault.jpg","videoCount":18,"channelTitle":"Elzero Web School","categories":["programming"],"path":"data/playlists/chunk_001/p319.json"},{"id":"p320","title":"Learn JavaScript in Arabic 2021","thumbnail":"https://i.ytimg.com/vi/GM6dQBmc-Xg/hqdefault.jpg","videoCount":188,"channelTitle":"Elzero Web School","categories":["programming","web","backend"],"path":"data/playlists/chunk_001/p320.json"},{"id":"p321","title":"HTML And CSS Template 2","thumbnail":"https://i.ytimg.com/vi/7_USXxmn7DM/hqdefault.jpg","videoCount":23,"channelTitle":"Elzero Web School","categories":["programming","web","backend"],"path":"data/playlists/chunk_001/p321.json"},{"id":"p322","title":"Front-End Tutorials","thumbnail":"https://i.ytimg.com/vi/e4P15Wc0wq8/hqdefault.jpg","videoCount":35,"channelTitle":"Elzero Web School","categories":["programming","web","frontend"],"path":"data/playlists/chunk_001/p322.json"},{"id":"p323","title":"HTML And CSS Template 1","thumbnail":"https://i.ytimg.com/vi/MBq8ZFEIIaQ/hqdefault.jpg","videoCount":14,"channelTitle":"Elzero Web School","categories":["programming","web","frontend"],"path":"data/playlists/chunk_001/p323.json"},{"id":"p324","title":"Learn CSS In Arabic 2021","thumbnail":"https://i.ytimg.com/vi/X1ulCwyhCVM/hqdefault.jpg","videoCount":88,"channelTitle":"Elzero Web School","categories":["programming","web","frontend"],"path":"data/playlists/chunk_001/p324.json"},{"id":"p325","title":"Learn HTML In Arabic 2021","thumbnail":"https://i.ytimg.com/vi/6QAELgirvjs/hqdefault.jpg","videoCount":37,"channelTitle":"Elzero Web School","categories":["programming","web","frontend"],"path":"data/playlists/chunk_001/p325.json"},{"id":"p326","title":"Intro To Programming","thumbnail":"https://i.ytimg.com/vi/9QC-PFHo8Yw/hqdefault.jpg","videoCount":4,"channelTitle":"Elzero Web School","categories":["programming"],"path":"data/playlists/chunk_001/p326.json"},{"id":"p327","title":"Mastering Laravel","thumbnail":"https://i.ytimg.com/vi/bXjRQM_VK_I/hqdefault.jpg","videoCount":21,"channelTitle":"Elzero Web School","categories":["programming"],"path":"data/playlists/chunk_001/p327.json"},{"id":"p328","title":"Python Learn By Examples","thumbnail":"https://i.ytimg.com/vi/lSRBhjLzNWw/hqdefault.jpg","videoCount":2,"channelTitle":"Elzero Web School","categories":["programming"],"path":"data/playlists/chunk_001/p328.json"},{"id":"p329","title":"JavaScript Unit Testing With Jest","thumbnail":"https://i.ytimg.com/vi/I5ba6jpRNh8/hqdefault.jpg","videoCount":20,"channelTitle":"Elzero Web School","categories":["programming"],"path":"data/playlists/chunk_001/p329.json"},{"id":"p330","title":"Create Template With HTML, CSS3, JavaScript","thumbnail":"https://i.ytimg.com/vi/vedT2jk3hi4/hqdefault.jpg","videoCount":38,"channelTitle":"Elzero Web School","categories":["programming","web","frontend"],"path":"data/playlists/chunk_001/p330.json"},{"id":"p331","title":"Mastering Python - تعلم بايثون","thumbnail":"https://i.ytimg.com/vi/mvZHDpCHphk/hqdefault.jpg","videoCount":152,"channelTitle":"Elzero Web School","categories":["programming"],"path":"data/playlists/chunk_001/p331.json"},{"id":"p332","title":"Learn Canvas API","thumbnail":"https://i.ytimg.com/vi/JdEfIRa8Srw/hqdefault.jpg","videoCount":14,"channelTitle":"Elzero Web School","categories":["programming","web","frontend"],"path":"data/playlists/chunk_001/p332.json"},{"id":"p333","title":"Learn AJAX","thumbnail":"https://i.ytimg.com/vi/6tLeMfOxIyA/hqdefault.jpg","videoCount":12,"channelTitle":"Elzero Web School","categories":["programming","web","backend"],"path":"data/playlists/chunk_001/p333.json"},{"id":"p334","title":"Learn JSON and Deal With API's","thumbnail":"https://i.ytimg.com/vi/CLpmD7hxiBs/hqdefault.jpg","videoCount":11,"channelTitle":"Elzero Web School","categories":["programming","web","backend"],"path":"data/playlists/chunk_001/p334.json"},{"id":"p335","title":"Vue.js Tutorials & Examples","thumbnail":"https://i.ytimg.com/vi/jXFSv12nUhI/hqdefault.jpg","videoCount":15,"channelTitle":"Elzero Web School","categories":["programming","web"],"path":"data/playlists/chunk_001/p335.json"},{"id":"p336","title":"The Ultimate Front-End Practical Course","thumbnail":"https://i.ytimg.com/vi/mTpsdebd1qA/hqdefault.jpg","videoCount":27,"channelTitle":"Elzero Web School","categories":["programming","web","frontend"],"path":"data/playlists/chunk_001/p336.json"},{"id":"p337","title":"Learn ECMAScript 6","thumbnail":"https://i.ytimg.com/vi/DcyOVddJ62E/hqdefault.jpg","videoCount":52,"channelTitle":"Elzero Web School","categories":["programming","web","backend"],"path":"data/playlists/chunk_001/p337.json"},{"id":"p338","title":"Learn Command Line","thumbnail":"https://i.ytimg.com/vi/JVs2Ywy7wGQ/hqdefault.jpg","videoCount":8,"channelTitle":"Elzero Web School","categories":["programming"],"path":"data/playlists/chunk_001/p338.json"},{"id":"p339","title":"Learn Git and Github","thumbnail":"https://i.ytimg.com/vi/ACOiGZoqC8w/hqdefault.jpg","videoCount":20,"channelTitle":"Elzero Web School","categories":["programming"],"path":"data/playlists/chunk_001/p339.json"},{"id":"p340","title":"JavaScript Big Tutorials","thumbnail":"https://i.ytimg.com/vi/AeXkyj4mXms/hqdefault.jpg","videoCount":31,"channelTitle":"Elzero Web School","categories":["programming","web","backend"],"path":"data/playlists/chunk_001/p340.json"},{"id":"p341","title":"Automatic Your Work With Gulpjs","thumbnail":"https://i.ytimg.com/vi/BLFndK5n29I/hqdefault.jpg","videoCount":18,"channelTitle":"Elzero Web School","categories":["programming","web"],"path":"data/playlists/chunk_001/p341.json"},{"id":"p342","title":"PHP Multiple Upload Script","thumbnail":"https://i.ytimg.com/vi/1R4lyINqYfc/hqdefault.jpg","videoCount":7,"channelTitle":"Elzero Web School","categories":["programming","web","backend"],"path":"data/playlists/chunk_001/p342.json"},{"id":"p343","title":"How To Become A Front-End Monster","thumbnail":"https://i.ytimg.com/vi/2qZiBnbY4DQ/hqdefault.jpg","videoCount":4,"channelTitle":"Elzero Web School","categories":["programming","web","frontend"],"path":"data/playlists/chunk_001/p343.json"},{"id":"p344","title":"Begin Working With PugJs","thumbnail":"https://i.ytimg.com/vi/txOuCrg7iOE/hqdefault.jpg","videoCount":21,"channelTitle":"Elzero Web School","categories":["programming","web","frontend"],"path":"data/playlists/chunk_001/p344.json"},{"id":"p345","title":"Secure Your PHP Web Application","thumbnail":"https://i.ytimg.com/vi/Rpd5uDXwpsU/hqdefault.jpg","videoCount":18,"channelTitle":"Elzero Web School","categories":["programming","web","backend"],"path":"data/playlists/chunk_001/p345.json"},{"id":"p346","title":"How To","thumbnail":"https://i.ytimg.com/vi/N3PgO0JjIbI/hqdefault.jpg","videoCount":20,"channelTitle":"Elzero Web School","categories":["programming"],"path":"data/playlists/chunk_001/p346.json"},{"id":"p347","title":"Create Web Design With Sass","thumbnail":"https://i.ytimg.com/vi/u4TY0TIxjZo/hqdefault.jpg","videoCount":28,"channelTitle":"Elzero Web School","categories":["programming","web"],"path":"data/playlists/chunk_001/p347.json"},{"id":"p348","title":"Multilingual Website Best Practice","thumbnail":"https://i.ytimg.com/vi/gpelGUckCtM/hqdefault.jpg","videoCount":9,"channelTitle":"Elzero Web School","categories":["programming","web"],"path":"data/playlists/chunk_001/p348.json"},{"id":"p349","title":"jQuery Practical Examples","thumbnail":"https://i.ytimg.com/vi/66QpkBLJ4_k/hqdefault.jpg","videoCount":53,"channelTitle":"Elzero Web School","categories":["programming","web","backend"],"path":"data/playlists/chunk_001/p349.json"},{"id":"p350","title":"Design Using Bootstrap 4 Design 1","thumbnail":"https://i.ytimg.com/vi/DbUjq8J6RK8/hqdefault.jpg","videoCount":29,"channelTitle":"Elzero Web School","categories":["programming","web","frontend"],"path":"data/playlists/chunk_001/p350.json"},{"id":"p351","title":"Hacker Rank Problems Solving","thumbnail":"https://i.ytimg.com/vi/tJl36vQtA5k/hqdefault.jpg","videoCount":10,"channelTitle":"Elzero Web School","categories":["programming"],"path":"data/playlists/chunk_001/p351.json"},{"id":"p352","title":"Design Using Bootstrap 3 Design 2","thumbnail":"https://i.ytimg.com/vi/SwCQTLB2zoo/hqdefault.jpg","videoCount":23,"channelTitle":"Elzero Web School","categories":["programming","web","frontend"],"path":"data/playlists/chunk_001/p352.json"},{"id":"p353","title":"Create Responsive Web Design Without Framework","thumbnail":"https://i.ytimg.com/vi/IjY-BZQHqLA/hqdefault.jpg","videoCount":21,"channelTitle":"Elzero Web School","categories":["programming","web"],"path":"data/playlists/chunk_001/p353.json"},{"id":"p354","title":"Learn Website Wireframing","thumbnail":"https://i.ytimg.com/vi/clZVDmKtTlU/hqdefault.jpg","videoCount":7,"channelTitle":"Elzero Web School","categories":["programming","web","frontend"],"path":"data/playlists/chunk_001/p354.json"},{"id":"p355","title":"Learn Object Oriented PHP","thumbnail":"https://i.ytimg.com/vi/w6JqPsVP7Ps/hqdefault.jpg","videoCount":35,"channelTitle":"Elzero Web School","categories":["programming"],"path":"data/playlists/chunk_001/p355.json"},{"id":"p356","title":"Create Contact Form with PHP, Bootstrap and jQuery","thumbnail":"https://i.ytimg.com/vi/vtgLbd-HSs4/hqdefault.jpg","videoCount":13,"channelTitle":"Elzero Web School","categories":["programming","web","backend"],"path":"data/playlists/chunk_001/p356.json"},{"id":"p357","title":"Mastering Wordpress [ In Progress ]","thumbnail":"https://i.ytimg.com/vi/ctEAYHFcbHk/hqdefault.jpg","videoCount":113,"channelTitle":"Elzero Web School","categories":["programming","web"],"path":"data/playlists/chunk_001/p357.json"},{"id":"p358","title":"Begin Working with Sass","thumbnail":"https://i.ytimg.com/vi/gDTkkMdT6r0/hqdefault.jpg","videoCount":23,"channelTitle":"Elzero Web School","categories":["programming","web"],"path":"data/playlists/chunk_001/p358.json"},{"id":"p359","title":"Learn Javascript Bom","thumbnail":"https://i.ytimg.com/vi/cMW4963o6Qo/hqdefault.jpg","videoCount":19,"channelTitle":"Elzero Web School","categories":["programming"],"path":"data/playlists/chunk_001/p359.json"},{"id":"p360","title":"Advanced Html & Css Lessons","thumbnail":"https://i.ytimg.com/vi/MBxm7SH7pzM/hqdefault.jpg","videoCount":11,"channelTitle":"Elzero Web School","categories":["programming","web","frontend"],"path":"data/playlists/chunk_001/p360.json"},{"id":"p361","title":"Learn Javascript HTML DOM","thumbnail":"https://i.ytimg.com/vi/LlQC9sU0coM/hqdefault.jpg","videoCount":38,"channelTitle":"Elzero Web School","categories":["programming","web","backend"],"path":"data/playlists/chunk_001/p361.json"},{"id":"p362","title":"MySQL 5 Essential Training","thumbnail":"https://i.ytimg.com/vi/DftlOK7fCtc/hqdefault.jpg","videoCount":51,"channelTitle":"Elzero Web School","categories":["programming","web","backend"],"path":"data/playlists/chunk_001/p362.json"},{"id":"p363","title":"Create eCommerce Shop With PHP, MySQL, jQuery, Bootstrap","thumbnail":"https://i.ytimg.com/vi/YajM38Dc3Qk/hqdefault.jpg","videoCount":128,"channelTitle":"Elzero Web School","categories":["programming","web"],"path":"data/playlists/chunk_001/p363.json"},{"id":"p364","title":"Creating A Website From Preview [ Html, Css3, jQuery Lv3 ]","thumbnail":"https://i.ytimg.com/vi/6olupGFs9DA/hqdefault.jpg","videoCount":17,"channelTitle":"Elzero Web School","categories":["programming","web","frontend"],"path":"data/playlists/chunk_001/p364.json"},{"id":"p365","title":"Creating A Website From Preview [ Html, Css, jQuery Lv2 ]","thumbnail":"https://i.ytimg.com/vi/52s6c4kYx-Y/hqdefault.jpg","videoCount":18,"channelTitle":"Elzero Web School","categories":["programming","web","frontend"],"path":"data/playlists/chunk_001/p365.json"},{"id":"p366","title":"Learn HTML5 In Arabic","thumbnail":"https://i.ytimg.com/vi/6gjg5n9kyBU/hqdefault.jpg","videoCount":36,"channelTitle":"Elzero Web School","categories":["programming","web","frontend"],"path":"data/playlists/chunk_001/p366.json"},{"id":"p367","title":"Javascript Examples & Tutorials","thumbnail":"https://i.ytimg.com/vi/GT58LOLcfvY/hqdefault.jpg","videoCount":17,"channelTitle":"Elzero Web School","categories":["programming","web","backend"],"path":"data/playlists/chunk_001/p367.json"},{"id":"p368","title":"PHP Examples & Tutorials","thumbnail":"https://i.ytimg.com/vi/lOsqte6vzro/hqdefault.jpg","videoCount":12,"channelTitle":"Elzero Web School","categories":["programming","web","backend"],"path":"data/playlists/chunk_001/p368.json"},{"id":"p369","title":"Learn PHP 5 In Arabic","thumbnail":"https://i.ytimg.com/vi/-u9_T_CLZHY/hqdefault.jpg","videoCount":103,"channelTitle":"Elzero Web School","categories":["programming","web","backend"],"path":"data/playlists/chunk_001/p369.json"},{"id":"p370","title":"Learn JavaScript In Arabic","thumbnail":"https://i.ytimg.com/vi/eKuNnpWhm7c/hqdefault.jpg","videoCount":65,"channelTitle":"Elzero Web School","categories":["programming","web","backend"],"path":"data/playlists/chunk_001/p370.json"},{"id":"p371","title":"Creating A Website From Preview [ Html, Css Lv1 ]","thumbnail":"https://i.ytimg.com/vi/urQihL3GTnw/hqdefault.jpg","videoCount":16,"channelTitle":"Elzero Web School","categories":["programming","web","frontend"],"path":"data/playlists/chunk_001/p371.json"},{"id":"p372","title":"Learn CSS3 In Arabic","thumbnail":"https://i.ytimg.com/vi/aBlZ_2rGeb4/hqdefault.jpg","videoCount":56,"channelTitle":"Elzero Web School","categories":["programming","web","frontend"],"path":"data/playlists/chunk_001/p372.json"},{"id":"p373","title":"Learn HTML In Arabic","thumbnail":"https://i.ytimg.com/vi/PYjyg0LNTfE/hqdefault.jpg","videoCount":24,"channelTitle":"Elzero Web School","categories":["programming","web","frontend"],"path":"data/playlists/chunk_001/p373.json"},{"id":"p374","title":"Design Using Bootstrap 3 Design 1","thumbnail":"https://i.ytimg.com/vi/auFVttzUoo8/hqdefault.jpg","videoCount":52,"channelTitle":"Elzero Web School","categories":["programming","web","frontend"],"path":"data/playlists/chunk_001/p374.json"},{"id":"p375","title":"jQuery Examples & Tutorials","thumbnail":"https://i.ytimg.com/vi/7CujDfLwsGU/hqdefault.jpg","videoCount":15,"channelTitle":"Elzero Web School","categories":["programming","web","frontend"],"path":"data/playlists/chunk_001/p375.json"},{"id":"p376","title":"Learn jQuery in Arabic","thumbnail":"https://i.ytimg.com/vi/JLm1ELLqJkA/hqdefault.jpg","videoCount":53,"channelTitle":"Elzero Web School","categories":["programming","web"],"path":"data/playlists/chunk_001/p376.json"},{"id":"p377","title":"Learn CSS In Arabic","thumbnail":"https://i.ytimg.com/vi/Iu1T7j2FA4M/hqdefault.jpg","videoCount":29,"channelTitle":"Elzero Web School","categories":["programming","web","frontend"],"path":"data/playlists/chunk_001/p377.json"},{"id":"p378","title":"Web Design Tutorials","thumbnail":"https://i.ytimg.com/vi/D7m-cb5nDk8/hqdefault.jpg","videoCount":55,"channelTitle":"Elzero Web School","categories":["programming","web","frontend"],"path":"data/playlists/chunk_001/p378.json"}]}