{"youtubeChannelId":"106","channelId":"9","channelTitle":"Learn Unity بالعربي","playlists":[{"id":"p91","title":"تعلم سي شارب للبرمجة على unity","thumbnail":"https://i.ytimg.com/vi/H0hPxBRWh_4/hqdefault.jpg","videoCount":1,"categories":["programming","unity"],"path":"data/playlists/chunk_002/p91.json"},{"id":"p92","title":"صنع لعبة","thumbnail":"https://i.ytimg.com/vi/3jvXnm-lykU/hqdefault.jpg","videoCount":4,"categories":["programming","unity"],"path":"data/playlists/chunk_002/p92.json"},{"id":"p93","title":"تعلم Unity3d من الاساسيات الى الاحتراف","thumbnail":"https://i.ytimg.com/vi/xojKMFPGKXA/hqdefault.jpg","videoCount":17,"categories":["programming","unity"],"path":"data/playlists/chunk_002/p93.json"}]}