{"id":"p2235","title":"سلسة تأثيرات الخطوط - TEXT Effects IN PIXELLAB","thumbnail":"https://i.ytimg.com/vi/I8DI-gyPAaI/hqdefault.jpg","videoCount":2,"channelTitle":"MR_GRD","channelId":"22","youtubePlaylistId":"PLs-hceiryD_i0igO-T3-ZYYIbe1FvxC9C","categories":["design"],"videos":[{"id":"1","youtubeVideoId":"I8DI-gyPAaI","title":"تأثيرات الخطوط - TEXT Effects IN PIXELLAB","description":"TEXT Effects IN PIXELLAB\nاول فيديو في سلسة تأثيرات الخطوط ببرنامج بيكسلاب . \nهنتعلم فيه تأثير Classy Text Effect \nمتنساش الشير واللايك وكومنتات عشان الخميس اللي جاي هختار اكثر واحد عامل لايك وشير وكومنتات عشان يفوز بلوجو مجاني \n#GRD #تأثيرات_الخطوط #PIXELLAB\n\nقناة التليجرام لتحميل الخط المستخدم\nhttps://t.me/kbac5","date":"2022-07-02T13:05:38Z","thumbnail":"https://i.ytimg.com/vi/I8DI-gyPAaI/hqdefault.jpg"},{"id":"2","youtubeVideoId":"kZjw5TbwS4s","title":"تأثير 3D TEXT مع انعكاس ببرنامج بيكسلاب للاندرويد - 3D TEXT effect with Pixellab for Android","description":"تأثير 3D TEXT مع انعكاس ببرنامج بيكسلاب للاندرويد بطريقه سهله وبسيطه خطوه بخطوه . 3D TEXT effect with Pixellab for Android\n\nقناة التليجرام لتحميل الملحقات \nhttps://t.me/kbac5","date":"2022-07-19T14:13:12Z","thumbnail":"https://i.ytimg.com/vi/kZjw5TbwS4s/hqdefault.jpg"}]}