{"id":"p3543","title":"قواعد البيانات ربط سكول سيرفر مع سي شارب بسرعة","thumbnail":"https://i.ytimg.com/vi/NMXn8s-GQ7Q/hqdefault.jpg","videoCount":2,"channelTitle":"Hassouna Academy","channelId":"35","youtubePlaylistId":"PLHIfW1KZRIfl9s420UMJyYR5dZ2tU4B6k","categories":["programming"],"videos":[{"id":"1","youtubeVideoId":"NMXn8s-GQ7Q","title":"01انشاء برنامج سى شارب وسكول سيرفر جزء 1Create Program With C Sharp And SQL Server  Part1","description":"اكاديمية حسونة - ادخل سجل في موقع ويب الاكاديمية من الرابط التالي\nhttps://www.hassouna-academy.com/\n01انشاء برنامج سى شارب وسكول سيرفر جزء 1Create Program With C Sharp And SQL Server  Part1","date":"2022-01-29T07:06:37Z","thumbnail":"https://i.ytimg.com/vi/NMXn8s-GQ7Q/hqdefault.jpg"},{"id":"2","youtubeVideoId":"ODTO1vSjJvw","title":"02انشاء برنامج سى شارب وسكول سيرفر جزء 2Create Program With C Sharp And SQL Server  Part2","description":"اكاديمية حسونة - ادخل سجل في موقع ويب الاكاديمية من الرابط التالي\nhttps://www.hassouna-academy.com/\n02انشاء برنامج سى شارب وسكول سيرفر جزء 2Create Program With C Sharp And SQL Server  Part2","date":"2022-01-29T07:06:51Z","thumbnail":"https://i.ytimg.com/vi/ODTO1vSjJvw/hqdefault.jpg"}]}